COPYING
LICENSE
MANIFEST.in
README.rst
setup.cfg
setup.py
doc/Pianofish User Guide.pdf
src/org.fedora.pianofish.gschema.xml
src/org.fedora.pianofish1.conf
src/org.fedora.pianofish1.policy
src/org.fedora.pianofish1.service
src/pianofish.desktop
src/pianofish.svg
src/bin/pianofish
src/pianofish/__init__.py
src/pianofish/bitmap.py
src/pianofish/ethtool.py
src/pianofish/irqview.py
src/pianofish/pciview.py
src/pianofish/pianofish_dbus.py
src/pianofish/pianofish_gui.py
src/pianofish/pianofish_server.py
src/pianofish/processview.py
src/pianofish/systemview.py
src/pianofish/translation.py
src/pianofish/utilities.py
src/pianofish.egg-info/PKG-INFO
src/pianofish.egg-info/SOURCES.txt
src/pianofish.egg-info/dependency_links.txt
src/pianofish.egg-info/requires.txt
src/pianofish.egg-info/top_level.txt
translations/locale/en_US/LC_MESSAGES/pianofish.po