Metadata-Version: 1.1
Name: pianofish
Version: 1.0.1
Summary: pianofish process management tool
Home-page: https://gitlab.com/guystreeter/pianofish
Author: Guy Streeter
Author-email: guy.streeter@gmail.com
License: GPLv2+
Platform: UNKNOWN
Classifier: Environment :: X11 Applications :: GTK
Classifier: Development Status :: 5 - Production/Stable
Classifier: Intended Audience :: System Administrators
Classifier: License :: OSI Approved :: GNU General Public License v2 or later (GPLv2+)
Classifier: Operating System :: POSIX :: Linux
Classifier: Programming Language :: Python
Classifier: Topic :: System :: Systems Administration
